[{"text": "excvtn", "checked_state": false}, {"text": "backfilling", "checked_state": false}, {"text": "dispsl", "checked_state": false}, {"text": "C25 Plain conc in fdn", "checked_state": false}, {"text": "blkwk", "checked_state": false}, {"text": "12mm plastering", "checked_state": false}, {"text": "C25 Rfc onc slab", "checked_state": false}, {"text": "20mm plastering", "checked_state": false}, {"text": "painting", "checked_state": false}, {"text": "12mm dia rft", "checked_state": false}, {"text": "metal cover", "checked_state": false}, {"text": "100mm PVC pipe", "checked_state": false}, {"text": "150mm screed", "checked_state": false}, {"text": "test", "checked_state": true}]